setup.py
diderot/OWL.py
diderot/__init__.py
diderot/assertion.py
diderot/case.py
diderot/inference.py
diderot/utils.py
diderot.egg-info/PKG-INFO
diderot.egg-info/SOURCES.txt
diderot.egg-info/dependency_links.txt
diderot.egg-info/requires.txt
diderot.egg-info/top_level.txt