Metadata-Version: 1.0
Name: diderot
Version: 0.1
Summary: Diderot - Test Driven Development for RDF/OWL Ontologies
Home-page: http://github.com/icaromedeiros/diderot
Author: Icaro Medeiros
Author-email: icaro.medeiros@gmail.com
License: PSF
Platform: Python 2.6 and newer
